tabular_log/__init__.py
tabular_log-2.7.dist-info/METADATA
tabular_log-2.7.dist-info/WHEEL
tabular_log-2.7.dist-info/top_level.txt
tabular_log-2.7.dist-info/zip-safe
tabular_log-2.7.dist-info/RECORD
