Metadata-Version: 2.1
Name: tabular-log
Version: 2.7
Summary: Creates and manage a tabular log.
Home-page: https://github.com/CastellaniDavide/tabular_log
Author: CastellaniDavide
Author-email: help@castellanidavide.it
License: GNU
Platform: linux_distibution
